iotile/__init__.py
iotile/build/__init__.py
iotile/build/config_variables.py
iotile/build/plugin.py
iotile/build/build/__init__.py
iotile/build/build/build.py
iotile/build/build/depends.py
iotile/build/config/site_scons/__init__.py
iotile/build/config/site_scons/arm.py
iotile/build/config/site_scons/autobuild.py
iotile/build/config/site_scons/cfileparser.py
iotile/build/config/site_scons/dependencies.py
iotile/build/config/site_scons/docbuild.py
iotile/build/config/site_scons/pythondist.py
iotile/build/config/site_scons/release.py
iotile/build/config/site_scons/site_init.py
iotile/build/config/site_scons/templates.py
iotile/build/config/site_scons/test_summary.py
iotile/build/config/site_scons/trub_script.py
iotile/build/config/site_scons/unit_test.py
iotile/build/config/site_scons/unit_test_qemu.py
iotile/build/config/site_scons/utilities.py
iotile/build/config/templates/command_map_c.c.tpl
iotile/build/config/templates/command_map_c.h.tpl
iotile/build/config/templates/config_variables_c.c.tpl
iotile/build/config/templates/config_variables_c.h.tpl
iotile/build/config/templates/doxygen.txt.tpl
iotile/build/config/templates/setup.py.tpl
iotile/build/config/templates/qemu_semihost_unit/main.c.tpl
iotile/build/config/templates/qemu_semihost_unit/qemu_semihost.ld
iotile/build/config/templates/qemu_semihost_unit/semihost.c
iotile/build/config/templates/qemu_semihost_unit/semihost.h
iotile/build/config/templates/qemu_semihost_unit/startup.c
iotile/build/config/templates/qemu_semihost_unit/unity.c
iotile/build/config/templates/qemu_semihost_unit/unity.h
iotile/build/config/templates/qemu_semihost_unit/unity_config.h
iotile/build/config/templates/qemu_semihost_unit/unity_internals.h
iotile/build/dev/__init__.py
iotile/build/dev/depmanager.py
iotile/build/dev/pull_release.py
iotile/build/dev/resolverchain.py
iotile/build/dev/resolvers/__init__.py
iotile/build/dev/resolvers/depresolver.py
iotile/build/dev/resolvers/registry_resolver.py
iotile/build/doc/__init__.py
iotile_build-3.2.0.dist-info/LICENSE.md
iotile_build-3.2.0.dist-info/METADATA
iotile_build-3.2.0.dist-info/WHEEL
iotile_build-3.2.0.dist-info/entry_points.txt
iotile_build-3.2.0.dist-info/top_level.txt
iotile_build-3.2.0.dist-info/RECORD
